MANIFEST.in
README.md
setup.cfg
setup.py
bin/create-shell-archive.sh
bin/encrypt-and-mount.sh
bin/ensure-letsencrypt-certs.sh
bin/lastpass-fetch-notes.sh
bin/lpssh
bin/setup-fetch-secrets.sh
bin/ssh-hostkeys-collect.sh
n_utils/__init__.py
n_utils/account_utils.py
n_utils/aws_infra_util.py
n_utils/cf_bootstrap.py
n_utils/cf_deploy.py
n_utils/cf_utils.py
n_utils/cli.py
n_utils/cloudfront_utils.py
n_utils/ecr_utils.py
n_utils/git_utils.py
n_utils/log_events.py
n_utils/maven_utils.py
n_utils/mfa_utils.py
n_utils/ndt.py
n_utils/ndt_project.py
n_utils/nitor-dt-enable-profile.py
n_utils/nitor-dt-load-project-env.py
n_utils/profile_util.py
n_utils/project_util.py
n_utils/volumes.py
n_utils/yuuuu3332111i1l1i.py
n_utils/includes/apache_tools.sh
n_utils/includes/autocomplete-helpers.sh
n_utils/includes/aws_tools.sh
n_utils/includes/bake-docker.sh
n_utils/includes/bake-image.sh
n_utils/includes/bake-image.yml
n_utils/includes/bake-tags.yaml
n_utils/includes/bake-win-image.yml
n_utils/includes/cloud-init-firewall-cmd.te
n_utils/includes/cloud_init_footer.sh
n_utils/includes/cloud_init_functions.sh
n_utils/includes/common_tools.sh
n_utils/includes/deploy-cdk.sh
n_utils/includes/deploy-serverless.sh
n_utils/includes/deploy-stack.sh
n_utils/includes/deploy-terraform.sh
n_utils/includes/disk-by-drive-letter.ps1
n_utils/includes/ebs-functions.sh
n_utils/includes/fail2ban-rundir.te
n_utils/includes/fetch-secrets-lpass.sh
n_utils/includes/fetch-secrets-s3.sh
n_utils/includes/fetch-secrets-vault.sh
n_utils/includes/hook.sh
n_utils/includes/install_tools.sh
n_utils/includes/jenkins_tools.sh
n_utils/includes/lastpass-login.sh
n_utils/includes/lastpass-logout.sh
n_utils/includes/letsencrypt.sh
n_utils/includes/lpass_centos_7
n_utils/includes/lpass_ubuntu_14.04
n_utils/includes/lpass_ubuntu_16.04
n_utils/includes/lpass_ubuntu_16.10
n_utils/includes/lpass_ubuntu_17.04
n_utils/includes/manage-account.yaml
n_utils/includes/nexus_tools.sh
n_utils/includes/prepare.ps1
nitor_deploy_tools.egg-info/PKG-INFO
nitor_deploy_tools.egg-info/SOURCES.txt
nitor_deploy_tools.egg-info/dependency_links.txt
nitor_deploy_tools.egg-info/entry_points.txt
nitor_deploy_tools.egg-info/not-zip-safe
nitor_deploy_tools.egg-info/requires.txt
nitor_deploy_tools.egg-info/top_level.txt