Metadata-Version: 1.1
Name: nitor-deploy-tools
Version: 1.60
Summary: Tools for deploying to AWS via CloudFormation and Serverless framework that support a pull request based workflow
Home-page: http://github.com/NitorCreations/nitor-deploy-tools
Author: Pasi Niemi
Author-email: pasi@nitor.com
License: Apache 2.0
Download-URL: https://github.com/NitorCreations/nitor-deploy-tools/tarball/1.60
Platform: UNKNOWN
